csv_tools
