Metadata-Version: 1.1
Name: csv-tools
Version: 0.4
Summary: Tools for working with delimited files.
Home-page: https://github.com/cw-andrews/csv_tools
Author: cw-andrews
Author-email: cwandrews.oh@gmail.com
License: MIT
Keywords: csv,delimited,csv_tools
Platform: UNKNOWN
Classifier: Development Status :: 2 - Pre-Alpha
Classifier: Intended Audience :: Developers
Classifier: License :: OSI Approved :: MIT License
Classifier: Natural Language :: English
Classifier: Programming Language :: Python :: 2
Classifier: Programming Language :: Python :: 2.7
Classifier: Programming Language :: Python :: 3
Classifier: Programming Language :: Python :: 3.3
Classifier: Programming Language :: Python :: 3.4
Classifier: Programming Language :: Python :: 3.5
